thejoyofpynting/__init__.py
thejoyofpynting/bobtypes.py
thejoyofpynting/bottypes.py
thejoyofpynting/paintapicture.py
thejoyofpynting-1.4.1.dist-info/DESCRIPTION.rst
thejoyofpynting-1.4.1.dist-info/METADATA
thejoyofpynting-1.4.1.dist-info/RECORD
thejoyofpynting-1.4.1.dist-info/WHEEL
thejoyofpynting-1.4.1.dist-info/metadata.json
thejoyofpynting-1.4.1.dist-info/top_level.txt
