Metadata-Version: 2.0
Name: thejoyofpynting
Version: 1.4.1
Summary: A Python library that will make Bob Ross paint any given image.
Home-page: https://github.com/DeflatedPickle/thejoyofpynting
Author: DeflatedPickle/Dibbo
Author-email: DeflatedPickle@gmail.com
License: MIT
Keywords: thejoyofpynting,bob,ross,bob ross
Platform: UNKNOWN
Classifier: Intended Audience :: Developers
Classifier: License :: OSI Approved :: MIT License
Classifier: Programming Language :: Python :: 3.4
Classifier: Programming Language :: Python :: 3.5
Requires-Dist: pillow
